csv_reconcile_geo/__init__.py
csv_reconcile_geo-0.1.6.dist-info/entry_points.txt
csv_reconcile_geo-0.1.6.dist-info/LICENSE
csv_reconcile_geo-0.1.6.dist-info/WHEEL
csv_reconcile_geo-0.1.6.dist-info/METADATA
csv_reconcile_geo-0.1.6.dist-info/RECORD
