Metadata-Version: 2.1
Name: csv-reconcile-geo
Version: 0.1.6
Summary: Geo distance scoring plugin for csv-reconcile
Home-page: https://github.com/gitonthescene/csv-reconcile-geo
License: MIT
Keywords: OpenRefine,reconcile,fuzzy search,gis,geooding,geocode
Author: Douglas Mennella
Author-email: trx2358-pypi@yahoo.com
Requires-Python: >=3.7,<4.0
Classifier: License :: OSI Approved :: MIT License
Classifier: Programming Language :: Python :: 3
Classifier: Programming Language :: Python :: 3.7
Classifier: Programming Language :: Python :: 3.8
Requires-Dist: csv-reconcile (>=0.2.1,<0.3.0)
Requires-Dist: geopy (>=2.1.0,<3.0.0)
Project-URL: Repository, https://github.com/gitonthescene/csv-reconcile-geo
